README.rst
setup.py
designer/__init__.py
designer/render.py
designer/management/__init__.py
designer/management/commands/__init__.py
designer/management/commands/render_template.py
django_designer.egg-info/PKG-INFO
django_designer.egg-info/SOURCES.txt
django_designer.egg-info/dependency_links.txt
django_designer.egg-info/not-zip-safe
django_designer.egg-info/requires.txt
django_designer.egg-info/top_level.txt