Metadata-Version: 1.0
Name: django-designer
Version: 0.2.1
Summary: Django template renderer for designers
Home-page: https://github.com/lander2k2/django-designer
Author: Richard Lander
Author-email: lander2k2@gmail.com
License: MIT
Platform: UNKNOWN
